Metadata-Version: 2.1
Name: Quickvisual
Version: 0.0.1
Summary: Basic Python charts wrapper
Home-page: UNKNOWN
Author: Liudmila Danilovskaya
License: UNKNOWN
Platform: UNKNOWN
